Metadata-Version: 1.0
Name: PyCodebase
Version: 0.7
Summary: A client for the Codebase API.
Home-page: https://github.com/davidwtbuxton/pycodebase
Author: David Buxton
Author-email: david@gasmark6.com
License: MIT
Platform: UNKNOWN
